api_layer/__init__.py
api_layer/api.py
api_layer/tencent_cloud.py
ApiLayer-0.0.6.dist-info/LICENSE
ApiLayer-0.0.6.dist-info/METADATA
ApiLayer-0.0.6.dist-info/WHEEL
ApiLayer-0.0.6.dist-info/top_level.txt
ApiLayer-0.0.6.dist-info/RECORD
