Metadata-Version: 2.1
Name: ApiLayer
Version: 0.0.6
Summary: Basic Api Layer
Home-page: https://github.com/lipopo/api_layer
Author: lipo
Author-email: lipo8081@gmail.com
License: UNKNOWN
Platform: UNKNOWN
Classifier: Programming Language :: Python :: 3
Classifier: License :: OSI Approved :: MIT License
Classifier: Operating System :: OS Independent
Requires-Python: >3.0
Requires-Dist: flask
Requires-Dist: requests
